popgen/__init__.py
popgen/cli.py
popgen/config.py
popgen/data.py
popgen/draw.py
popgen/ipf.py
popgen/output.py
popgen/project.py
popgen/reweighting.py
popgen3-3.0.4.dist-info/METADATA
popgen3-3.0.4.dist-info/WHEEL
popgen3-3.0.4.dist-info/entry_points.txt
popgen3-3.0.4.dist-info/top_level.txt
popgen3-3.0.4.dist-info/RECORD
