Metadata-Version: 2.4
Name: popgen3
Version: 3.0.4
Summary: A population synthesis and sample weighting tool for transportation planning.
Home-page: https://github.com/chnfanyu/PopGen3
Author: Fan Yu
Author-email: fanyu4@asu.edu
Classifier: Development Status :: 4 - Beta
Classifier: Intended Audience :: Science/Research
Classifier: Intended Audience :: Developers
Classifier: License :: OSI Approved :: MIT License
Classifier: Programming Language :: Python :: 3
Classifier: Programming Language :: Python :: 3.9
Classifier: Operating System :: OS Independent
Classifier: Topic :: Scientific/Engineering :: Artificial Intelligence
Classifier: Topic :: Scientific/Engineering :: Information Analysis
Requires-Python: >=3.8
Requires-Dist: pyyaml>=6.0
Requires-Dist: numpy>=1.21.6
Requires-Dist: pandas>=1.3.0
Requires-Dist: scipy>=1.10.1
Dynamic: author
Dynamic: author-email
Dynamic: classifier
Dynamic: description
Dynamic: description-content-type
Dynamic: home-page
Dynamic: requires-dist
Dynamic: requires-python
Dynamic: summary
